Workbook

Sheet Client Info
A1: CALCULATIONS TOOL
A7: Quotation Tool for FlexMax Capital Appreciator Fixed Deposit Note 1 Year Term
A9: CLIENT NUMBER: | F9: OFDN-104-778-004
A11: CLIENT NAME: | F11: Marilyn Kannemeyer
A12: ADDRESS: | F12: 25 Kanna Road
F13: Belhar
F14: Western Cape
F15: 7493
F16: 0728882033
A18: OFFERED TO: | F18: =F11 -> Marilyn Kannemeyer
A19: INVESTMENT AMOUNT: | F19: 75000
A24: DATE OF CALCULATION: | F24: =TODAY() -> 46056
A25: COMMENCEMENT DATE OF PLAN | F25: 45962
A26: TERM IN YEARS | F26: 1
A27: REDEMPTION DATE | F27: 46326
A30: PREPARED BY: | F30: Lionel Lottering
F31: Cell: 076 309 2590
F32: Office: 0861 263 346
F33: Email: lionell@opianfsgroup.com

Sheet FDN_CapAPP_1-Year
B12: Quotation for FlexMax Capital Appreciator Fixed Deposit Note 1 Year Term
B14: Date of Offer: | E14: ='Client Info'!F24 -> 46056
B16: Offered to: | E16: ='Client Info'!F11 -> Marilyn Kannemeyer
B17: Adress: | E17: ='Client Info'!F12 -> 25 Kanna Road
E18: ='Client Info'!F13 -> Belhar
E19: {='Client Info'!F14:F14} -> Western Cape
E20: ='Client Info'!F15 -> 7493
B21: Telephone: | E21: ='Client Info'!F16 -> 0728882033
B22: Email:
B24: Dear | C24: ='Client Info'!F11 -> Marilyn Kannemeyer
B26: We take pleasure in submitting the following proposal to you:
B28: Investment summary
B29: Investment amount | K29: ='Client Info'!F19 -> 75000
B30: Amount allocated with enhancement | K30: =K29+'Client Info'!F21 -> 75000
B31: Term in years | K31: ='Client Info'!F26 -> 1
B32: Commencement date | K32: ='Client Info'!F25 -> 45962
B33: Percentage returned first year | K33: =I50 -> 0.0975
B34: Income allocated to capital in first year | K34: =J50 -> 7312.5
B35: Liquidity | K35: None
B37: Contract Start date | K37: ='Client Info'!F25 -> 45962
B38: Exit date | K38: ='Client Info'!F27 -> 46326
B39: Return Cycle | K39: Annually
B40: Capital allocation | K40: 1
B43: Registered Adress: 210 Amarand Avenue, Waterkloof Glen, 0181, Menlyn, Pretoria | H43: Fund Adress: Sovereign Trust International Limited.
B44: Email: info@opiancapital.com Website: www.opiancapital.com | H44: Sovereign Place, 117 Main Street, GX11 1AA, Gibraltar, GI
B46: Income projections
B47: Year | C47: Projection Scenarios
C48: Capital Value | I48: Return Forecast
C49: Current | I49: Projected | K49: Annualised
B50: 1 | C50: =K30 -> 75000 | I50: =Sheet1!D5 -> 0.0975 | J50: =C50*I50 -> 7312.5 | K50: =C50+J50 -> 82312.5
B54: Modelled Fund Choices
B55: ISIN | D55: Fund Name | H55: Type | J55: Split
B56: ISIN Code GG00B3TBCS61 | D56: WSF Global Equity Fund | H56: Risk-Adverse | J56: 1
B58: * | C58: Please note that fund choices will be modeled and should the dividends below these returns, the modeled returns will be payable to the client.
B60: Conditions:
B61: 1. To effectively evaluate this product against comparable alternatives, it is essential to analyze and contrast its risk and
B62: reward profile with those of similar products offering analogous risk-reward structures.
B64: 2. This offer involves the purchase of Fixed Deposit Notes FDN's in private equity. Given the inherent risks associated
B65: we strongly recommend independent advice before making any commitment.
B67: 3. This offer contains no guarantees beyond those expressly stated herein. Upon signing, the terms outlined in this offer
B68: shall constitute a legally binding agreement between the client and the company.
A70: 4. The applicant acknowledges understanding of the complexities involving this investment
B71: as well as the lock-in periods contained in the investment
A73: 5. The applicant understands that a loan agreement will come into existence after signature of this quotation
B74: and that returns paid are mirrored on the performance of the selected fund above.
B76: 6. The applicant understands the zero liquidity nature of this investment and has ensured that he has enough alternative
B77: liquid investments or savings to ensure liquidity during this investment .
B79: 7. The applicant understands that the directors or trustees of company funds, in their collective capacity, may
B80: limit, withold, defer or reduce payments or payouts as necessary at moment's notice to safeguard the company's liquidity
B81: requirements and ensure financial stability.
B83: 8. The individual, individuals or organisation/s entering into this agreement acknowledges and understands that this is
B84: a fixed-term contract, as specified in the duration outlined above. The term "Exit Date" refers to the agreed-upon end date
B85: of the agreement.
B87: 9. The applicant understands that if shares are issued under this agreement, the shares are issued for security only and
B88: are returnable when the applicant is paid back his invested capital.
B90: 10. The applicant retains the option to convert their capital to fixed shares at exit date; whereafter the par value of
B91: the converted shares will be based on a comprehensive company's valuation at the time of exit.
I95: CLIENT SIGN
B97: Validity:
B98: This offer remains valid for a period of 14 days from the date of issuance. It is imperative that the receipt of funds occurs
B99: within this specific time frame. All required documentation must be completed, and funds transfers finalized, on or before the
B100: expiration of the offer's validity period. Should any information remain outstanding or incomplete, funds will be processed, but
B101: a new offer must be issued and duly executed before the terms can be formally accepted by the company.
B103: Taxation:
B104: Taxation is not addressed in this plan. Taxation should be discussed with a tax adviser.
B106: Fees:
B107: This offer details the fees payable under the contract, which encompass deal placement fees. (commissions)
B109: Suitability:
B110: The client's access to capital are restricted for the duration of this agreement. As such, it is imperative that the client
B111: maintains a financial position robust enough to support the terms and obligations outlined herein, such term also being the
... B123: The Placement and Admin fees amount shown below are paid nett of VAT
C125: Placement Fees
C126: Placement fee | J126: 1.00% once off
C127: Admin Fees | H127: Once Off | J127: 3.50%
B130: Commission
B131: The Commission amount shown below are paid nett of VAT
C133: Commission
C134: Commission | F134: First Year 0.50% | J134: 0.50%
B138: Offer Prepared By: | D138: ='Client Info'!F30 -> Lionel Lottering
D139: ='Client Info'!F31 -> Cell: 076 309 2590
D140: ='Client Info'!F32 -> Office: 0861 263 346
D141: ='Client Info'!F33 -> Email: lionell@opianfsgroup.com
A151: SUBSCRIPTION FORM
B156: Agreement number: | D156: ='Client Info'!F9 -> OFDN-104-778-004 | G156: ='Client Info'!F11 -> Marilyn Kannemeyer
B158: I, the undersigned, by my signature below, hereby accept the above quotation and confirm that this quotation will form the
B159: basis of my agreement with the company. I confirm that the amount will be invested and I confirm herewith by my signature
B160: below that this will constitute a legal, valid and binding obligation to the issuer enforceable in accordance with its terms.
B163: Signature of Investor:
B167: PLEASE ATTACH THE FOLLOWING SUPPORT DOCUMENTATION:
B169: Application form
B171: Copy of Identity Document / Passport:
B173: Proof of Address:
B175: Bank Statement:

Sheet Sheet1
D2: YEARLY
D3: DIV
D4: ALLOCATION
B5: 1. | D5: 0.0975
